lannerpsp/__init__.py
lannerpsp/core.py
lannerpsp/exc.py
lannerpsp/gpio_config_tool.py
lannerpsp/lmbinc.py
lannerpsp/lmbipmi.py
lannerpsp/lmbsid.py
lannerpsp/sdk_can.py
lannerpsp/sdk_dll.py
lannerpsp/sdk_eep.py
lannerpsp/sdk_gpio.py
lannerpsp/sdk_gps.py
lannerpsp/sdk_gsr.py
lannerpsp/sdk_hwm.py
lannerpsp/sdk_ign.py
lannerpsp/sdk_lbp.py
lannerpsp/sdk_lcm.py
lannerpsp/sdk_odm_com_port.py
lannerpsp/sdk_poe.py
lannerpsp/sdk_psu.py
lannerpsp/sdk_rfm.py
lannerpsp/sdk_sled.py
lannerpsp/sdk_sled_gps.py
lannerpsp/sdk_sled_lte.py
lannerpsp/sdk_sled_lte_stress.py
lannerpsp/sdk_swr.py
lannerpsp/sdk_wdt.py
lannerpsp/utils.py
lannerpsp-0.0.15.dist-info/LICENSE
lannerpsp-0.0.15.dist-info/METADATA
lannerpsp-0.0.15.dist-info/WHEEL
lannerpsp-0.0.15.dist-info/top_level.txt
lannerpsp-0.0.15.dist-info/RECORD
