Metadata-Version: 2.1
Name: lannerpsp
Version: 0.0.15
Summary: Python API for Lanner PSP
Author: UFO Chen
Author-email: ufo_chen@lannerinc.com
License: MIT License
Project-URL: homepage, https://github.com/lanneriotsw/psp-api-python
Project-URL: documentation, https://psp-api-python.readthedocs.io/
Project-URL: repository, https://github.com/lanneriotsw/psp-api-python
Project-URL: changelog, https://psp-api-python.readthedocs.io/en/stable/changelog.html
Keywords: lanner,psp
Platform: Linux
Classifier: Development Status :: 3 - Alpha
Classifier: Intended Audience :: Customer Service
Classifier: Intended Audience :: Developers
Classifier: License :: OSI Approved :: MIT License
Classifier: Operating System :: POSIX :: Linux
Classifier: Programming Language :: Python
Classifier: Programming Language :: Python :: 3
Classifier: Programming Language :: Python :: 3 :: Only
Classifier: Programming Language :: Python :: 3.6
Classifier: Programming Language :: Python :: 3.7
Classifier: Programming Language :: Python :: 3.8
Classifier: Programming Language :: Python :: 3.9
Classifier: Programming Language :: Python :: 3.10
Classifier: Programming Language :: Python :: 3.11
Classifier: Programming Language :: Python :: 3.12
Requires-Python: >=3.6
License-File: LICENSE
Provides-Extra: all
Requires-Dist: portio ==0.5 ; extra == 'all'
Provides-Extra: dev
Requires-Dist: build ; extra == 'dev'
Requires-Dist: setuptools ; extra == 'dev'
Requires-Dist: twine ; extra == 'dev'
Provides-Extra: doc
Requires-Dist: sphinx <8 ; extra == 'doc'
Requires-Dist: sphinx-rtd-theme ; extra == 'doc'
Requires-Dist: toml ; extra == 'doc'
Provides-Extra: portio
Requires-Dist: portio ==0.5 ; extra == 'portio'
Provides-Extra: test
Requires-Dist: pytest ; extra == 'test'
